<?xml version="1.0" encoding="utf-8"?>
<!-- generated by Altova XMLSpy 2020 rel. 2 sp1 (x64) (http://www.altova.com) -->
<xbrli:xbrl xmlns:gl-plt="http://www.xbrl.org/int/gl/plt/2020-12-31" xmlns:xbrll="http://www.xbrl.org/2003/linkbase" xmlns:iso639="http://www.xbrl.org/2005/iso639" xmlns:gl-cor="http://www.xbrl.org/int/gl/cor/2020-12-31" xmlns:eg="http://www.xbrl.org/xbrlgl/sample" xmlns:gl-muc="http://www.xbrl.org/int/gl/muc/2020-12-31" xmlns:xbrldi="http://xbrl.org/2006/xbrldi" xmlns:xsi="http://www.w3.org/2001/XMLSchema-instance" xmlns:xbrli="http://www.xbrl.org/2003/instance" xmlns:iso4217="http://www.xbrl.org/2003/iso4217" xmlns:xlink="http://www.w3.org/1999/xlink" xmlns:gl-bus="http://www.xbrl.org/int/gl/bus/2020-12-31">
	<xbrll:schemaRef xlink:type="simple" xlink:href="../plt/case-c-b-m-u-t/gl-plt-all-2020-12-31.xsd"/>
	<xbrli:context id="context1">
		<xbrli:entity>
			<xbrli:identifier scheme="http://www.xbrl.org/xbrlgl/sample">SAMPLE</xbrli:identifier>
			<xbrli:segment>
				<xbrldi:typedMember dimension="gl-cor:dEntryNumber">
					<gl-cor:EntryNumber>H2</gl-cor:EntryNumber>
				</xbrldi:typedMember>
				<xbrldi:typedMember dimension="gl-cor:dLineNumber">
					<gl-cor:LineNumber>3</gl-cor:LineNumber>
				</xbrldi:typedMember>
			</xbrli:segment>
		</xbrli:entity>
		<xbrli:period>
			<xbrli:instant>2004-10-03</xbrli:instant>
		</xbrli:period>
	</xbrli:context>
	<xbrli:unit id="unit1">
		<xbrli:measure>iso4217:USD</xbrli:measure>
	</xbrli:unit>
	<gl-cor:amount contextRef="context1" unitRef="unit1" precision="0">500</gl-cor:amount>
	<xbrli:context id="context2">
		<xbrli:entity>
			<xbrli:identifier scheme="http://www.xbrl.org/xbrlgl/sample">SAMPLE</xbrli:identifier>
			<xbrli:segment>
				<xbrldi:typedMember dimension="gl-cor:dEntryNumber">
					<gl-cor:EntryNumber>H1</gl-cor:EntryNumber>
				</xbrldi:typedMember>
				<xbrldi:typedMember dimension="gl-cor:dLineNumber">
					<gl-cor:LineNumber>1</gl-cor:LineNumber>
				</xbrldi:typedMember>
			</xbrli:segment>
		</xbrli:entity>
		<xbrli:period>
			<xbrli:instant>2004-10-03</xbrli:instant>
		</xbrli:period>
	</xbrli:context>
	<gl-cor:amount contextRef="context2" unitRef="unit1" precision="0">5000</gl-cor:amount>
	<xbrli:context id="context3">
		<xbrli:entity>
			<xbrli:identifier scheme="http://www.xbrl.org/xbrlgl/sample">SAMPLE</xbrli:identifier>
			<xbrli:segment>
				<xbrldi:typedMember dimension="gl-cor:dEntryNumber">
					<gl-cor:EntryNumber>H1</gl-cor:EntryNumber>
				</xbrldi:typedMember>
				<xbrldi:typedMember dimension="gl-cor:dLineNumber">
					<gl-cor:LineNumber>3</gl-cor:LineNumber>
				</xbrldi:typedMember>
			</xbrli:segment>
		</xbrli:entity>
		<xbrli:period>
			<xbrli:instant>2004-10-03</xbrli:instant>
		</xbrli:period>
	</xbrli:context>
	<gl-cor:amount contextRef="context3" unitRef="unit1" precision="0">6000</gl-cor:amount>
	<xbrli:context id="context4">
		<xbrli:entity>
			<xbrli:identifier scheme="http://www.xbrl.org/xbrlgl/sample">SAMPLE</xbrli:identifier>
			<xbrli:segment>
				<xbrldi:typedMember dimension="gl-cor:dEntryNumber">
					<gl-cor:EntryNumber>H2</gl-cor:EntryNumber>
				</xbrldi:typedMember>
				<xbrldi:typedMember dimension="gl-cor:dLineNumber">
					<gl-cor:LineNumber>1</gl-cor:LineNumber>
				</xbrldi:typedMember>
			</xbrli:segment>
		</xbrli:entity>
		<xbrli:period>
			<xbrli:instant>2004-10-03</xbrli:instant>
		</xbrli:period>
	</xbrli:context>
	<gl-cor:amount contextRef="context4" unitRef="unit1" precision="0">500</gl-cor:amount>
</xbrli:xbrl>
